scomix/README.md
scomix/__init__.py
scomix/config.py
scomix/version
scomix/rna/__init__.py
scomix/rna/counts.py
scomix-0.0.1.dist-info/LICENSE
scomix-0.0.1.dist-info/METADATA
scomix-0.0.1.dist-info/WHEEL
scomix-0.0.1.dist-info/top_level.txt
scomix-0.0.1.dist-info/RECORD
