Metadata-Version: 2.1
Name: scomix
Version: 0.0.1
Summary: Python package for analysis of data from single-cell data-science.
Home-page: https://github.com/rahulbhadani/scomix
Author: Rahul Bhadani
Author-email: rahulbhadani@email.arizona.edu
License: UNKNOWN
Keywords: single-cell,scRNAseq,transcriptomics,atacseq,rnaseq,bioinformatics,life-sciences,computation-biology,data-science,system-biology
Platform: UNKNOWN
Classifier: Programming Language :: Python :: 3
Classifier: Framework :: IPython
Classifier: Topic :: Scientific/Engineering :: Bio-Informatics
Classifier: Topic :: Scientific/Engineering :: Visualization
Classifier: Topic :: Scientific/Engineering :: Medical Science Apps.
Classifier: License :: OSI Approved :: MIT License
Requires-Dist: modin (==0.8.2)
Requires-Dist: modin[ray]
Requires-Dist: scanpy (==1.5.1)
Requires-Dist: scipy (==1.5.4)
